rpegment/__init__.py
rpegment/app.py
rpegment/assets/style.css
rpegment/cell.py
rpegment/src/__init__.py
rpegment/src/components/__init__.py
rpegment/src/components/analysis.py
rpegment/src/components/control.py
rpegment/src/components/ids.py
rpegment/src/components/image.py
rpegment/src/components/layout.py
rpegment/src/components/raw.py
rpegment/src/components/segment.py
rpegment-1.0.2.dist-info/METADATA
rpegment-1.0.2.dist-info/WHEEL
rpegment-1.0.2.dist-info/RECORD
